myrlkit/__init__.py
myrlkit/agents/__init__.py
myrlkit/agents/bandit.py
myrlkit/agents/q_learning.py
myrlkit/agents/sarsa.py
myrlkit/envs/__init__.py
myrlkit/envs/bandit.py
myrlkit/envs/gridworld.py
myrlkit-0.1.2.dist-info/licenses/LICENSE
myrlkit-0.1.2.dist-info/METADATA
myrlkit-0.1.2.dist-info/WHEEL
myrlkit-0.1.2.dist-info/top_level.txt
myrlkit-0.1.2.dist-info/RECORD
