Metadata-Version: 2.4
Name: myrlkit
Version: 0.1.2
Summary: A tiny, teaching-focused reinforcement learning kit (Q-learning, SARSA, Bandits) with toy environments.
Author: Nihar Lohar
License: MIT
Project-URL: Homepage,  https://www.linkedin.com/in/nihar-lohar-20234a287/
Project-URL: Source, https://github.com/yourusername/myrlkit
Classifier: Development Status :: 3 - Alpha
Classifier: Intended Audience :: Education
Classifier: License :: OSI Approved :: MIT License
Classifier: Programming Language :: Python :: 3
Classifier: Programming Language :: Python :: 3 :: Only
Classifier: Topic :: Scientific/Engineering :: Artificial Intelligence
Requires-Python: >=3.9
License-File: LICENSE
Requires-Dist: numpy>=1.22
Requires-Dist: matplotlib>=3.5
Dynamic: license-file
